bibliometria/__init__.py
bibliometria/data_utils.py
bibliometria/journal_data.py
bibliometria/metrics.py
bibliometria/metrics_utils.py
bibliometria/data/sjr_journals_2024.csv
bibliometria/data/wos_journals.csv
bibliometria-0.1.0.dist-info/METADATA
bibliometria-0.1.0.dist-info/WHEEL
bibliometria-0.1.0.dist-info/RECORD
