Metadata-Version: 2.4
Name: bibliometria
Version: 0.1.0
Summary: A package for bibliometric analysis of journals
Project-URL: Homepage, https://github.com/VTermus/bibliometria
Author-email: Vladislava Termus <vl.trmus@gmail.com>, Alexandra Pogozheva <sashapogozheva04@gmail.com>
License-Expression: GPL-3.0
Classifier: Development Status :: 3 - Alpha
Classifier: Intended Audience :: Science/Research
Classifier: License :: OSI Approved :: GNU General Public License v3 (GPLv3)
Classifier: Operating System :: OS Independent
Classifier: Programming Language :: Python :: 3
Classifier: Programming Language :: Python :: 3.9
Classifier: Programming Language :: Python :: 3.10
Classifier: Programming Language :: Python :: 3.11
Classifier: Programming Language :: Python :: 3.12
Classifier: Topic :: Scientific/Engineering
Classifier: Topic :: Scientific/Engineering :: Information Analysis
Classifier: Topic :: Software Development :: Libraries :: Python Modules
Requires-Python: >=3.9
Requires-Dist: pandas>=1.5
Requires-Dist: rapidfuzz>=3.0
